LICENSE
README.md
setup.py
Flask_Events.egg-info/PKG-INFO
Flask_Events.egg-info/SOURCES.txt
Flask_Events.egg-info/dependency_links.txt
Flask_Events.egg-info/requires.txt
Flask_Events.egg-info/top_level.txt
flask_events/__init__.py
flask_events/_version.py
flask_events/anonymizer.py
flask_events/events.py
flask_events/utils.py
flask_events/outlets/__init__.py
flask_events/outlets/libhoney.py
flask_events/outlets/logfmt.py
tests/__init__.py
tests/conftest.py
tests/test_anonymizer.py
tests/test_celery.py
tests/test_core.py
tests/test_libhoney_outlet.py
tests/test_logfmt_outlet.py
tests/test_sample_app.py
tests/test_utils.py