Metadata-Version: 2.1
Name: Flask-Events
Version: 0.7.0
Summary: Easy structured logging and metrics collection for Flask
Home-page: https://github.com/get-wrecked/flask-events
Author: Tarjei Husøy
Author-email: git@thusoy.com
License: Hippocratic-2.1
Classifier: Development Status :: 7 - Inactive
Classifier: Environment :: Web Environment
Classifier: Framework :: Flask
Classifier: Intended Audience :: Developers
Classifier: Intended Audience :: System Administrators
Classifier: Programming Language :: Python :: 3
Classifier: Programming Language :: Python :: 3 :: Only
Classifier: Programming Language :: Python :: 3.5
Classifier: Programming Language :: Python :: 3.6
Classifier: Programming Language :: Python :: 3.7
Classifier: Programming Language :: Python :: 3.8
Classifier: Topic :: System :: Logging
Classifier: Topic :: System :: Monitoring
Classifier: Topic :: Internet :: WWW/HTTP :: WSGI :: Application
License-File: LICENSE
Requires-Dist: libhoney>=1.3.0
